{
    "66": 245,
    "67": 261,
    "68": 262,
    "70": 266,
    "71": 267,
    "72": 271,
    "73": 273,
    "74": 272,
    "75": 274,
    "76": 279,
    "77": 280,
    "78": 281,
    "80": 282,
    "81": 297,
    "82": 298,
    "83": 311,
    "84": 307,
    "85": 315,
    "88": 316,
    "91": 319,
    "92": 321,
    "93": 332,
    "94": 340,
    "95": 343,
    "96": 345,
    "97": 346,
    "98": 347,
    "99": 350,
    "100": 371,
    "101": 392,
    "102": 401,
    "103": 399,
    "104": 421,
    "105": 444,
    "106": 453,
    "107": 436,
    "108": 458
}